<?xml version="1.0"?>
<shader_library file="fx/particle_vfx_library.hlsl"/><vfx construction_type="2" enable_in_ted="false" camera_following="false" affected_by_wind="false" spawn_on_terrain="false" ref_spawn_speed="-1.00">
	<!-- EMITTERS-->
	<emitters></emitters>
	<!-- BEHAVIOUR_CHAINS-->
	<behaviour_chains></behaviour_chains>
	<!-- EFFECT RENDER STACKS-->
	<effect_render_stacks></effect_render_stacks>
</vfx><vfx_references>
	<vfx inst_name="main" vfx_ref="wh_main_lib_cast_new" scale_min="1.00" scale_max="1.00" pos_x="0.00" pos_y="0.00" pos_z="0.00" rot_x="0.00" rot_y="0.00" rot_z="0.00" start_time_min="0.00" start_time_max="0.00" infinite_life="false">
		<emitter name="trail_wispy" enable="false" tint_min_r="1.00" tint_min_g="1.00" tint_min_b="1.00" tint_min_a="1.00" tint_max_r="1.00" tint_max_g="1.00" tint_max_b="1.00" tint_max_a="1.00" particle_lifetime_bias_min="0.00" particle_lifetime_bias_max="0.00" emitter_lifetime_bias_min="0.00" emitter_lifetime_bias_max="0.00"/>
		<emitter name="trail_wispy_overlay" enable="false" tint_min_r="1.00" tint_min_g="1.00" tint_min_b="1.00" tint_min_a="1.00" tint_max_r="1.00" tint_max_g="1.00" tint_max_b="1.00" tint_max_a="1.00" particle_lifetime_bias_min="0.00" particle_lifetime_bias_max="0.00" emitter_lifetime_bias_min="0.00" emitter_lifetime_bias_max="0.00"/>
		<emitter name="trail_smokeX" enable="false" tint_min_r="1.00" tint_min_g="1.00" tint_min_b="0.50" tint_min_a="1.00" tint_max_r="1.00" tint_max_g="1.00" tint_max_b="0.50" tint_max_a="1.00" particle_lifetime_bias_min="0.00" particle_lifetime_bias_max="0.00" emitter_lifetime_bias_min="0.00" emitter_lifetime_bias_max="0.00"/>
		<emitter name="trail_flame" enable="false" tint_min_r="1.00" tint_min_g="1.00" tint_min_b="1.00" tint_min_a="1.00" tint_max_r="1.00" tint_max_g="1.00" tint_max_b="1.00" tint_max_a="1.00" particle_lifetime_bias_min="0.00" particle_lifetime_bias_max="0.00" emitter_lifetime_bias_min="0.00" emitter_lifetime_bias_max="0.00"/>
		<emitter name="trail_splashes" enable="false" tint_min_r="1.00" tint_min_g="1.00" tint_min_b="1.00" tint_min_a="1.00" tint_max_r="1.00" tint_max_g="1.00" tint_max_b="1.00" tint_max_a="1.00" particle_lifetime_bias_min="0.00" particle_lifetime_bias_max="0.00" emitter_lifetime_bias_min="0.00" emitter_lifetime_bias_max="0.00"/>
		<emitter name="trail_embers" enable="false" tint_min_r="0.67" tint_min_g="1.00" tint_min_b="1.00" tint_min_a="2.00" tint_max_r="0.67" tint_max_g="1.00" tint_max_b="1.00" tint_max_a="2.00" particle_lifetime_bias_min="0.00" particle_lifetime_bias_max="0.00" emitter_lifetime_bias_min="-2.20" emitter_lifetime_bias_max="-2.20"/>
		<emitter name="trail_glow" enable="false" tint_min_r="1.00" tint_min_g="1.00" tint_min_b="0.50" tint_min_a="1.00" tint_max_r="1.00" tint_max_g="1.00" tint_max_b="0.50" tint_max_a="1.00" particle_lifetime_bias_min="0.00" particle_lifetime_bias_max="0.00" emitter_lifetime_bias_min="-2.20" emitter_lifetime_bias_max="-2.20"/>
		<emitter name="static_wispy" enable="false" tint_min_r="1.00" tint_min_g="1.00" tint_min_b="0.60" tint_min_a="0.70" tint_max_r="1.00" tint_max_g="1.00" tint_max_b="0.60" tint_max_a="0.70" particle_lifetime_bias_min="0.00" particle_lifetime_bias_max="0.00" emitter_lifetime_bias_min="-2.20" emitter_lifetime_bias_max="-2.20"/>
		<emitter name="static_flame" enable="false" tint_min_r="1.00" tint_min_g="1.00" tint_min_b="1.00" tint_min_a="1.00" tint_max_r="1.00" tint_max_g="1.00" tint_max_b="1.00" tint_max_a="1.00" particle_lifetime_bias_min="0.00" particle_lifetime_bias_max="0.00" emitter_lifetime_bias_min="0.00" emitter_lifetime_bias_max="0.00"/>
		<emitter name="static_glow" enable="false" tint_min_r="1.00" tint_min_g="1.00" tint_min_b="0.50" tint_min_a="0.70" tint_max_r="1.00" tint_max_g="1.00" tint_max_b="0.50" tint_max_a="0.70" particle_lifetime_bias_min="0.00" particle_lifetime_bias_max="0.00" emitter_lifetime_bias_min="-2.20" emitter_lifetime_bias_max="-2.20"/>
		<emitter name="static_embers" enable="false" tint_min_r="1.00" tint_min_g="1.00" tint_min_b="1.00" tint_min_a="1.00" tint_max_r="1.00" tint_max_g="1.00" tint_max_b="1.00" tint_max_a="1.00" particle_lifetime_bias_min="0.00" particle_lifetime_bias_max="0.00" emitter_lifetime_bias_min="0.00" emitter_lifetime_bias_max="0.00"/>
		<emitter name="static_sparks" enable="false" tint_min_r="1.00" tint_min_g="1.00" tint_min_b="0.50" tint_min_a="1.00" tint_max_r="1.00" tint_max_g="1.00" tint_max_b="0.50" tint_max_a="1.00" particle_lifetime_bias_min="0.00" particle_lifetime_bias_max="0.00" emitter_lifetime_bias_min="-2.20" emitter_lifetime_bias_max="-2.20"/>
		<emitter name="end_flash" enable="false" tint_min_r="1.00" tint_min_g="1.00" tint_min_b="1.00" tint_min_a="1.00" tint_max_r="1.00" tint_max_g="1.00" tint_max_b="1.00" tint_max_a="1.00" particle_lifetime_bias_min="0.00" particle_lifetime_bias_max="0.00" emitter_lifetime_bias_min="0.00" emitter_lifetime_bias_max="0.00"/>
		<emitter name="end_burst" enable="false" tint_min_r="1.00" tint_min_g="1.00" tint_min_b="1.00" tint_min_a="1.00" tint_max_r="1.00" tint_max_g="1.00" tint_max_b="1.00" tint_max_a="1.00" particle_lifetime_bias_min="0.00" particle_lifetime_bias_max="0.00" emitter_lifetime_bias_min="0.00" emitter_lifetime_bias_max="0.00"/>
		<emitter name="end_splashes" enable="false" tint_min_r="1.00" tint_min_g="1.00" tint_min_b="1.00" tint_min_a="1.00" tint_max_r="1.00" tint_max_g="1.00" tint_max_b="1.00" tint_max_a="1.00" particle_lifetime_bias_min="0.00" particle_lifetime_bias_max="0.00" emitter_lifetime_bias_min="0.00" emitter_lifetime_bias_max="0.00"/>
		<emitter name="end_embers" enable="false" tint_min_r="1.00" tint_min_g="1.00" tint_min_b="1.00" tint_min_a="1.00" tint_max_r="1.00" tint_max_g="1.00" tint_max_b="1.00" tint_max_a="1.00" particle_lifetime_bias_min="0.00" particle_lifetime_bias_max="0.00" emitter_lifetime_bias_min="0.00" emitter_lifetime_bias_max="0.00"/>
		<emitter name="omni_light" enable="false" tint_min_r="1.00" tint_min_g="1.00" tint_min_b="0.50" tint_min_a="1.00" tint_max_r="1.00" tint_max_g="1.00" tint_max_b="0.50" tint_max_a="1.00" particle_lifetime_bias_min="0.00" particle_lifetime_bias_max="0.00" emitter_lifetime_bias_min="-2.20" emitter_lifetime_bias_max="-2.20"/>
		<emitter name="Cast_vortex_small" enable="false" tint_min_r="1.00" tint_min_g="1.00" tint_min_b="1.00" tint_min_a="1.00" tint_max_r="1.00" tint_max_g="1.00" tint_max_b="1.00" tint_max_a="1.00" particle_lifetime_bias_min="0.00" particle_lifetime_bias_max="0.00" emitter_lifetime_bias_min="0.00" emitter_lifetime_bias_max="0.00"/>
		<emitter name="trail_death_charge" enable="false" tint_min_r="1.00" tint_min_g="1.00" tint_min_b="1.00" tint_min_a="1.00" tint_max_r="1.00" tint_max_g="1.00" tint_max_b="1.00" tint_max_a="1.00" particle_lifetime_bias_min="0.00" particle_lifetime_bias_max="0.00" emitter_lifetime_bias_min="0.00" emitter_lifetime_bias_max="0.00"/>
		<emitter name="static_lightning" enable="false" tint_min_r="1.00" tint_min_g="1.00" tint_min_b="1.00" tint_min_a="1.00" tint_max_r="1.00" tint_max_g="1.00" tint_max_b="1.00" tint_max_a="1.00" particle_lifetime_bias_min="0.00" particle_lifetime_bias_max="0.00" emitter_lifetime_bias_min="0.00" emitter_lifetime_bias_max="0.00"/>
		<emitter name="trail_sparks" enable="false" tint_min_r="1.00" tint_min_g="1.00" tint_min_b="1.00" tint_min_a="1.00" tint_max_r="1.00" tint_max_g="1.00" tint_max_b="1.00" tint_max_a="1.00" particle_lifetime_bias_min="0.00" particle_lifetime_bias_max="0.00" emitter_lifetime_bias_min="0.00" emitter_lifetime_bias_max="0.00"/>
		<emitter name="end_distortion" enable="false" tint_min_r="1.00" tint_min_g="1.00" tint_min_b="1.00" tint_min_a="1.00" tint_max_r="1.00" tint_max_g="1.00" tint_max_b="1.00" tint_max_a="1.00" particle_lifetime_bias_min="0.00" particle_lifetime_bias_max="0.00" emitter_lifetime_bias_min="0.00" emitter_lifetime_bias_max="0.00"/>
		<emitter name="static_pulse" enable="false" tint_min_r="1.00" tint_min_g="1.00" tint_min_b="1.00" tint_min_a="1.00" tint_max_r="1.00" tint_max_g="1.00" tint_max_b="1.00" tint_max_a="1.00" particle_lifetime_bias_min="0.00" particle_lifetime_bias_max="0.00" emitter_lifetime_bias_min="0.00" emitter_lifetime_bias_max="0.00"/>
		<emitter name="end_pulse" enable="false" tint_min_r="1.00" tint_min_g="1.00" tint_min_b="1.00" tint_min_a="1.00" tint_max_r="1.00" tint_max_g="1.00" tint_max_b="1.00" tint_max_a="1.00" particle_lifetime_bias_min="0.00" particle_lifetime_bias_max="0.00" emitter_lifetime_bias_min="0.00" emitter_lifetime_bias_max="0.00"/>
		<emitter name="static_vortex" enable="false" tint_min_r="1.00" tint_min_g="1.00" tint_min_b="1.00" tint_min_a="1.00" tint_max_r="1.00" tint_max_g="1.00" tint_max_b="1.00" tint_max_a="1.00" particle_lifetime_bias_min="0.00" particle_lifetime_bias_max="0.00" emitter_lifetime_bias_min="0.00" emitter_lifetime_bias_max="0.00"/>
		<emitter name="end_lightning" enable="false" tint_min_r="1.00" tint_min_g="1.00" tint_min_b="1.00" tint_min_a="1.00" tint_max_r="1.00" tint_max_g="1.00" tint_max_b="1.00" tint_max_a="1.00" particle_lifetime_bias_min="0.00" particle_lifetime_bias_max="0.00" emitter_lifetime_bias_min="0.00" emitter_lifetime_bias_max="0.00"/>
		<emitter name="static_flies" enable="false" tint_min_r="1.00" tint_min_g="1.00" tint_min_b="1.00" tint_min_a="1.00" tint_max_r="1.00" tint_max_g="1.00" tint_max_b="1.00" tint_max_a="1.00" particle_lifetime_bias_min="0.00" particle_lifetime_bias_max="0.00" emitter_lifetime_bias_min="0.00" emitter_lifetime_bias_max="0.00"/>
		<emitter name="static_smokey" enable="false" tint_min_r="1.00" tint_min_g="1.00" tint_min_b="1.00" tint_min_a="1.00" tint_max_r="1.00" tint_max_g="1.00" tint_max_b="1.00" tint_max_a="1.00" particle_lifetime_bias_min="0.00" particle_lifetime_bias_max="0.00" emitter_lifetime_bias_min="0.00" emitter_lifetime_bias_max="0.00"/>
	</vfx>
	<vfx inst_name="end_part" vfx_ref="wh_main_lib_cast_new" scale_min="1.00" scale_max="1.00" pos_x="0.00" pos_y="0.00" pos_z="0.00" rot_x="0.00" rot_y="0.00" rot_z="0.00" start_time_min="0.90" start_time_max="0.90" infinite_life="false">
		<emitter name="trail_wispy" enable="false" tint_min_r="1.00" tint_min_g="1.00" tint_min_b="1.00" tint_min_a="1.00" tint_max_r="1.00" tint_max_g="1.00" tint_max_b="1.00" tint_max_a="1.00" particle_lifetime_bias_min="0.00" particle_lifetime_bias_max="0.00" emitter_lifetime_bias_min="0.00" emitter_lifetime_bias_max="0.00"/>
		<emitter name="trail_wispy_overlay" enable="false" tint_min_r="1.00" tint_min_g="1.00" tint_min_b="1.00" tint_min_a="1.00" tint_max_r="1.00" tint_max_g="1.00" tint_max_b="1.00" tint_max_a="1.00" particle_lifetime_bias_min="0.00" particle_lifetime_bias_max="0.00" emitter_lifetime_bias_min="0.00" emitter_lifetime_bias_max="0.00"/>
		<emitter name="trail_smokeX" enable="false" tint_min_r="1.00" tint_min_g="1.00" tint_min_b="0.50" tint_min_a="1.00" tint_max_r="1.00" tint_max_g="1.00" tint_max_b="0.50" tint_max_a="1.00" particle_lifetime_bias_min="0.00" particle_lifetime_bias_max="0.00" emitter_lifetime_bias_min="0.00" emitter_lifetime_bias_max="0.00"/>
		<emitter name="trail_flame" enable="false" tint_min_r="1.00" tint_min_g="1.00" tint_min_b="1.00" tint_min_a="1.00" tint_max_r="1.00" tint_max_g="1.00" tint_max_b="1.00" tint_max_a="1.00" particle_lifetime_bias_min="0.00" particle_lifetime_bias_max="0.00" emitter_lifetime_bias_min="0.00" emitter_lifetime_bias_max="0.00"/>
		<emitter name="trail_splashes" enable="false" tint_min_r="1.00" tint_min_g="1.00" tint_min_b="1.00" tint_min_a="1.00" tint_max_r="1.00" tint_max_g="1.00" tint_max_b="1.00" tint_max_a="1.00" particle_lifetime_bias_min="0.00" particle_lifetime_bias_max="0.00" emitter_lifetime_bias_min="0.00" emitter_lifetime_bias_max="0.00"/>
		<emitter name="trail_embers" enable="false" tint_min_r="1.00" tint_min_g="1.00" tint_min_b="0.40" tint_min_a="1.00" tint_max_r="1.00" tint_max_g="1.00" tint_max_b="0.40" tint_max_a="1.00" particle_lifetime_bias_min="0.00" particle_lifetime_bias_max="0.00" emitter_lifetime_bias_min="0.00" emitter_lifetime_bias_max="0.00"/>
		<emitter name="trail_glow" enable="false" tint_min_r="1.00" tint_min_g="1.00" tint_min_b="0.50" tint_min_a="1.00" tint_max_r="1.00" tint_max_g="1.00" tint_max_b="0.50" tint_max_a="1.00" particle_lifetime_bias_min="0.00" particle_lifetime_bias_max="0.00" emitter_lifetime_bias_min="0.00" emitter_lifetime_bias_max="0.00"/>
		<emitter name="static_wispy" enable="false" tint_min_r="1.00" tint_min_g="1.00" tint_min_b="1.00" tint_min_a="1.00" tint_max_r="1.00" tint_max_g="1.00" tint_max_b="1.00" tint_max_a="1.00" particle_lifetime_bias_min="0.00" particle_lifetime_bias_max="0.00" emitter_lifetime_bias_min="0.00" emitter_lifetime_bias_max="0.00"/>
		<emitter name="static_flame" enable="false" tint_min_r="1.00" tint_min_g="1.00" tint_min_b="1.00" tint_min_a="1.00" tint_max_r="1.00" tint_max_g="1.00" tint_max_b="1.00" tint_max_a="1.00" particle_lifetime_bias_min="0.00" particle_lifetime_bias_max="0.00" emitter_lifetime_bias_min="0.00" emitter_lifetime_bias_max="0.00"/>
		<emitter name="static_glow" enable="false" tint_min_r="1.00" tint_min_g="1.00" tint_min_b="0.50" tint_min_a="1.00" tint_max_r="1.00" tint_max_g="1.00" tint_max_b="0.50" tint_max_a="1.00" particle_lifetime_bias_min="0.00" particle_lifetime_bias_max="0.00" emitter_lifetime_bias_min="0.00" emitter_lifetime_bias_max="0.00"/>
		<emitter name="static_embers" enable="false" tint_min_r="1.00" tint_min_g="1.00" tint_min_b="1.00" tint_min_a="1.00" tint_max_r="1.00" tint_max_g="1.00" tint_max_b="1.00" tint_max_a="1.00" particle_lifetime_bias_min="0.00" particle_lifetime_bias_max="0.00" emitter_lifetime_bias_min="0.00" emitter_lifetime_bias_max="0.00"/>
		<emitter name="static_sparks" enable="false" tint_min_r="1.00" tint_min_g="1.00" tint_min_b="0.50" tint_min_a="1.00" tint_max_r="1.00" tint_max_g="1.00" tint_max_b="0.50" tint_max_a="1.00" particle_lifetime_bias_min="0.00" particle_lifetime_bias_max="0.00" emitter_lifetime_bias_min="0.00" emitter_lifetime_bias_max="0.00"/>
		<emitter name="end_flash" enable="false" tint_min_r="1.00" tint_min_g="1.00" tint_min_b="0.50" tint_min_a="1.00" tint_max_r="1.00" tint_max_g="1.00" tint_max_b="0.50" tint_max_a="1.00" particle_lifetime_bias_min="0.00" particle_lifetime_bias_max="0.00" emitter_lifetime_bias_min="0.00" emitter_lifetime_bias_max="0.00"/>
		<emitter name="end_burst" enable="false" tint_min_r="0.67" tint_min_g="1.00" tint_min_b="1.00" tint_min_a="1.00" tint_max_r="0.67" tint_max_g="1.00" tint_max_b="1.00" tint_max_a="1.00" particle_lifetime_bias_min="0.00" particle_lifetime_bias_max="0.00" emitter_lifetime_bias_min="0.00" emitter_lifetime_bias_max="0.00"/>
		<emitter name="end_splashes" enable="false" tint_min_r="1.00" tint_min_g="1.00" tint_min_b="1.00" tint_min_a="1.00" tint_max_r="1.00" tint_max_g="1.00" tint_max_b="1.00" tint_max_a="1.00" particle_lifetime_bias_min="0.00" particle_lifetime_bias_max="0.00" emitter_lifetime_bias_min="0.00" emitter_lifetime_bias_max="0.00"/>
		<emitter name="end_embers" enable="false" tint_min_r="1.00" tint_min_g="0.67" tint_min_b="0.00" tint_min_a="1.00" tint_max_r="1.00" tint_max_g="0.67" tint_max_b="0.00" tint_max_a="1.00" particle_lifetime_bias_min="0.00" particle_lifetime_bias_max="0.00" emitter_lifetime_bias_min="0.00" emitter_lifetime_bias_max="0.00"/>
		<emitter name="omni_light" enable="false" tint_min_r="1.00" tint_min_g="1.00" tint_min_b="0.50" tint_min_a="1.00" tint_max_r="1.00" tint_max_g="1.00" tint_max_b="0.50" tint_max_a="1.00" particle_lifetime_bias_min="-0.40" particle_lifetime_bias_max="-0.40" emitter_lifetime_bias_min="-4.50" emitter_lifetime_bias_max="-4.50"/>
		<emitter name="Cast_vortex_small" enable="false" tint_min_r="1.00" tint_min_g="1.00" tint_min_b="1.00" tint_min_a="1.00" tint_max_r="1.00" tint_max_g="1.00" tint_max_b="1.00" tint_max_a="1.00" particle_lifetime_bias_min="0.00" particle_lifetime_bias_max="0.00" emitter_lifetime_bias_min="0.00" emitter_lifetime_bias_max="0.00"/>
		<emitter name="trail_death_charge" enable="false" tint_min_r="1.00" tint_min_g="1.00" tint_min_b="1.00" tint_min_a="1.00" tint_max_r="1.00" tint_max_g="1.00" tint_max_b="1.00" tint_max_a="1.00" particle_lifetime_bias_min="0.00" particle_lifetime_bias_max="0.00" emitter_lifetime_bias_min="0.00" emitter_lifetime_bias_max="0.00"/>
		<emitter name="static_lightning" enable="false" tint_min_r="1.00" tint_min_g="1.00" tint_min_b="1.00" tint_min_a="1.00" tint_max_r="1.00" tint_max_g="1.00" tint_max_b="1.00" tint_max_a="1.00" particle_lifetime_bias_min="0.00" particle_lifetime_bias_max="0.00" emitter_lifetime_bias_min="0.00" emitter_lifetime_bias_max="0.00"/>
		<emitter name="trail_sparks" enable="false" tint_min_r="1.00" tint_min_g="1.00" tint_min_b="1.00" tint_min_a="1.00" tint_max_r="1.00" tint_max_g="1.00" tint_max_b="1.00" tint_max_a="1.00" particle_lifetime_bias_min="0.00" particle_lifetime_bias_max="0.00" emitter_lifetime_bias_min="0.00" emitter_lifetime_bias_max="0.00"/>
		<emitter name="end_distortion" enable="false" tint_min_r="1.00" tint_min_g="1.00" tint_min_b="1.00" tint_min_a="1.00" tint_max_r="1.00" tint_max_g="1.00" tint_max_b="1.00" tint_max_a="1.00" particle_lifetime_bias_min="0.00" particle_lifetime_bias_max="0.00" emitter_lifetime_bias_min="0.00" emitter_lifetime_bias_max="0.00"/>
		<emitter name="static_pulse" enable="false" tint_min_r="1.00" tint_min_g="1.00" tint_min_b="1.00" tint_min_a="1.00" tint_max_r="1.00" tint_max_g="1.00" tint_max_b="1.00" tint_max_a="1.00" particle_lifetime_bias_min="0.00" particle_lifetime_bias_max="0.00" emitter_lifetime_bias_min="0.00" emitter_lifetime_bias_max="0.00"/>
		<emitter name="end_pulse" enable="false" tint_min_r="1.00" tint_min_g="1.00" tint_min_b="1.00" tint_min_a="1.00" tint_max_r="1.00" tint_max_g="1.00" tint_max_b="1.00" tint_max_a="1.00" particle_lifetime_bias_min="0.00" particle_lifetime_bias_max="0.00" emitter_lifetime_bias_min="0.00" emitter_lifetime_bias_max="0.00"/>
		<emitter name="static_vortex" enable="false" tint_min_r="1.00" tint_min_g="1.00" tint_min_b="1.00" tint_min_a="1.00" tint_max_r="1.00" tint_max_g="1.00" tint_max_b="1.00" tint_max_a="1.00" particle_lifetime_bias_min="0.00" particle_lifetime_bias_max="0.00" emitter_lifetime_bias_min="0.00" emitter_lifetime_bias_max="0.00"/>
		<emitter name="end_lightning" enable="false" tint_min_r="1.00" tint_min_g="1.00" tint_min_b="1.00" tint_min_a="1.00" tint_max_r="1.00" tint_max_g="1.00" tint_max_b="1.00" tint_max_a="1.00" particle_lifetime_bias_min="0.00" particle_lifetime_bias_max="0.00" emitter_lifetime_bias_min="0.00" emitter_lifetime_bias_max="0.00"/>
		<emitter name="static_flies" enable="false" tint_min_r="1.00" tint_min_g="1.00" tint_min_b="1.00" tint_min_a="1.00" tint_max_r="1.00" tint_max_g="1.00" tint_max_b="1.00" tint_max_a="1.00" particle_lifetime_bias_min="0.00" particle_lifetime_bias_max="0.00" emitter_lifetime_bias_min="0.00" emitter_lifetime_bias_max="0.00"/>
		<emitter name="static_smokey" enable="false" tint_min_r="1.00" tint_min_g="1.00" tint_min_b="1.00" tint_min_a="1.00" tint_max_r="1.00" tint_max_g="1.00" tint_max_b="1.00" tint_max_a="1.00" particle_lifetime_bias_min="0.00" particle_lifetime_bias_max="0.00" emitter_lifetime_bias_min="0.00" emitter_lifetime_bias_max="0.00"/>
	</vfx>
</vfx_references>